<?xml version="1.0" encoding="UTF-8"?><record_update table="sp_instance_table">
    <sp_instance_table action="DELETE">
        <active>true</active>
        <class_name/>
        <color>default</color>
        <css/>
        <display_field/>
        <field_list/>
        <filter/>
        <glyph/>
        <id/>
        <maximum_entries>5</maximum_entries>
        <order>4</order>
        <order_by/>
        <order_direction>asc</order_direction>
        <roles/>
        <short_description/>
        <size>md</size>
        <sp_column display_value="1">ce1fbe0e932496507f0af5f08bba1061</sp_column>
        <sp_page/>
        <sp_widget display_value="Table Reference">1dbb29f147001200ba13a5554ee49014</sp_widget>
        <sys_class_name>sp_instance_table</sys_class_name>
        <sys_created_by>admin</sys_created_by>
        <sys_created_on>2024-09-11 16:22:37</sys_created_on>
        <sys_id>5b41c38e932496507f0af5f08bba1051</sys_id>
        <sys_mod_count>0</sys_mod_count>
        <sys_name/>
        <sys_package display_value="Loaner Vehicle Request and Inventory" source="x_984902_lva">a025676893b302107f0af5f08bba103c</sys_package>
        <sys_policy/>
        <sys_scope display_value="Loaner Vehicle Request and Inventory">a025676893b302107f0af5f08bba103c</sys_scope>
        <sys_update_name>sp_instance_table_5b41c38e932496507f0af5f08bba1051</sys_update_name>
        <sys_updated_by>admin</sys_updated_by>
        <sys_updated_on>2024-09-11 16:22:37</sys_updated_on>
        <table/>
        <title/>
        <url/>
        <widget_parameters/>
    </sp_instance_table>
    <sys_translated_text action="DELETE" query="documentkey=5b41c38e932496507f0af5f08bba1051"/>
    <sys_update_version action="INSERT_OR_UPDATE">
        <action>DELETE</action>
        <application display_value="Loaner Vehicle Request and Inventory">a025676893b302107f0af5f08bba103c</application>
        <file_path/>
        <instance_id>751b4bbedb223d90caf99027c5961994</instance_id>
        <instance_name>dev218809</instance_name>
        <name>sp_instance_table_5b41c38e932496507f0af5f08bba1051</name>
        <payload><![CDATA[<?xml version="1.0" encoding="UTF-8"?><record_update table="sp_instance_table"><sp_instance_table action="INSERT_OR_UPDATE"><active>true</active><class_name/><color>default</color><css/><display_field/><field_list/><filter/><glyph/><id/><maximum_entries>5</maximum_entries><order>4</order><order_by/><order_direction>asc</order_direction><roles/><short_description/><size>md</size><sp_column display_value="1">ce1fbe0e932496507f0af5f08bba1061</sp_column><sp_page/><sp_widget display_value="Table Reference">1dbb29f147001200ba13a5554ee49014</sp_widget><sys_class_name>sp_instance_table</sys_class_name><sys_created_by>admin</sys_created_by><sys_created_on>2024-09-11 16:22:37</sys_created_on><sys_id>5b41c38e932496507f0af5f08bba1051</sys_id><sys_mod_count>0</sys_mod_count><sys_name/><sys_package display_value="Loaner Vehicle Request and Inventory" source="x_984902_lva">a025676893b302107f0af5f08bba103c</sys_package><sys_policy/><sys_scope display_value="Loaner Vehicle Request and Inventory">a025676893b302107f0af5f08bba103c</sys_scope><sys_update_name>sp_instance_table_5b41c38e932496507f0af5f08bba1051</sys_update_name><sys_updated_by>admin</sys_updated_by><sys_updated_on>2024-09-11 16:22:37</sys_updated_on><table/><title/><url/><widget_parameters/></sp_instance_table><sys_translated_text action="delete_multiple" query="documentkey=5b41c38e932496507f0af5f08bba1051"/></record_update>]]></payload>
        <payload_hash>1359358142</payload_hash>
        <record_name/>
        <reverted_from/>
        <source>3e792f2c93b302107f0af5f08bba107f</source>
        <source_table>sys_update_set</source_table>
        <state>previous</state>
        <sys_created_by>admin</sys_created_by>
        <sys_created_on>2024-09-11 16:22:37</sys_created_on>
        <sys_id>db41c38e932496507f0af5f08bba1053</sys_id>
        <sys_mod_count>0</sys_mod_count>
        <sys_recorded_at>191e1e4db9a0000001</sys_recorded_at>
        <sys_updated_by>admin</sys_updated_by>
        <sys_updated_on>2024-09-11 16:22:37</sys_updated_on>
        <type>Instance with Table</type>
        <update_guid>df41c38e67249650935c8cf012b57f52</update_guid>
        <update_guid_history>df41c38e67249650935c8cf012b57f52:1359358142</update_guid_history>
    </sys_update_version>
    <sys_metadata_delete action="INSERT_OR_UPDATE">
        <sys_audit_delete display_value="">5c61cf4e932496507f0af5f08bba1026</sys_audit_delete>
        <sys_class_name>sys_metadata_delete</sys_class_name>
        <sys_created_by>admin</sys_created_by>
        <sys_created_on>2024-09-11 16:22:57</sys_created_on>
        <sys_db_object display_value="" name="sp_instance_table">sp_instance_table</sys_db_object>
        <sys_id>584f246dac7b45af9f728e3e50e5eb29</sys_id>
        <sys_metadata>5b41c38e932496507f0af5f08bba1051</sys_metadata>
        <sys_mod_count>0</sys_mod_count>
        <sys_name/>
        <sys_package display_value="Loaner Vehicle Request and Inventory" source="x_984902_lva">a025676893b302107f0af5f08bba103c</sys_package>
        <sys_parent/>
        <sys_policy/>
        <sys_scope display_value="Loaner Vehicle Request and Inventory">a025676893b302107f0af5f08bba103c</sys_scope>
        <sys_scope_delete display_value="">3ec0fa50df594f7592b45e5b8a4908e9</sys_scope_delete>
        <sys_update_name>sp_instance_table_5b41c38e932496507f0af5f08bba1051</sys_update_name>
        <sys_update_version display_value="sp_instance_table_5b41c38e932496507f0af5f08bba1051">db41c38e932496507f0af5f08bba1053</sys_update_version>
        <sys_updated_by>admin</sys_updated_by>
        <sys_updated_on>2024-09-11 16:22:57</sys_updated_on>
    </sys_metadata_delete>
</record_update>
